.gitignore
.stylelintrc.json
LICENSE
MANIFEST.in
NEWS
README.md
setup.py
sphinx_lv2_theme/__init__.py
sphinx_lv2_theme/domainindex.html
sphinx_lv2_theme/genindex.html
sphinx_lv2_theme/globaltoc.html
sphinx_lv2_theme/layout.html
sphinx_lv2_theme/localtoc.html
sphinx_lv2_theme/page.html
sphinx_lv2_theme/search.html
sphinx_lv2_theme/theme.conf
sphinx_lv2_theme.egg-info/PKG-INFO
sphinx_lv2_theme.egg-info/SOURCES.txt
sphinx_lv2_theme.egg-info/dependency_links.txt
sphinx_lv2_theme.egg-info/entry_points.txt
sphinx_lv2_theme.egg-info/requires.txt
sphinx_lv2_theme.egg-info/top_level.txt
sphinx_lv2_theme/static/pygments.css
sphinx_lv2_theme/static/sphinx_lv2_theme.css_t