Metadata-Version: 2.4
Name: sphinx_lv2_theme
Version: 1.4.6
Summary: A minimal static theme for Sphinx
Home-page: https://gitlab.com/lv2/sphinx_lv2_theme
Author: David Robillard
Author-email: d@drobilla.net
License: ISC
Classifier: Framework :: Sphinx
Classifier: Framework :: Sphinx :: Theme
Classifier: Development Status :: 5 - Production/Stable
Classifier: Environment :: Console
Classifier: Environment :: Web Environment
Classifier: Intended Audience :: Developers
Classifier: Programming Language :: Python :: 3.6
Classifier: Operating System :: OS Independent
Classifier: Topic :: Documentation
Classifier: Topic :: Software Development :: Documentation
License-File: LICENSE
Requires-Dist: sphinx
Dynamic: author
Dynamic: author-email
Dynamic: classifier
Dynamic: description
Dynamic: description-content-type
Dynamic: home-page
Dynamic: license
Dynamic: license-file
Dynamic: requires-dist
Dynamic: summary
